strangeworks/__init__.py
strangeworks/sw_client.py
strangeworks/utils.py
strangeworks/core/__init__.py
strangeworks/core/utils.py
strangeworks/core/client/__init__.py
strangeworks/core/client/auth.py
strangeworks/core/client/backends.py
strangeworks/core/client/file.py
strangeworks/core/client/jobs.py
strangeworks/core/client/resource.py
strangeworks/core/client/rest_client.py
strangeworks/core/client/transport.py
strangeworks/core/client/workspace.py
strangeworks/core/config/__init__.py
strangeworks/core/config/base.py
strangeworks/core/config/config.py
strangeworks/core/config/defaults.py
strangeworks/core/config/env.py
strangeworks/core/config/file.py
strangeworks/core/errors/__init__.py
strangeworks/core/errors/error.py
strangeworks/platform/gql.py
strangeworks-0.7.6.dist-info/METADATA
strangeworks-0.7.6.dist-info/WHEEL
strangeworks-0.7.6.dist-info/licenses/LICENSE
strangeworks-0.7.6.dist-info/RECORD
