Metadata-Version: 2.4
Name: strangeworks
Version: 0.7.6
Summary: Strangeworks Python SDK
Author-email: Strange Devs <hello@strangeworks.com>
License-Expression: Apache-2.0
License-File: LICENSE
Requires-Python: >=3.11
Requires-Dist: python-jose[cryptography]>=3.3.0
Requires-Dist: pyyaml<7,>=6.0.0
Requires-Dist: requests-toolbelt<2,>=1.0.0
Requires-Dist: requests<3,>=2.30.0
Requires-Dist: strangeworks-core>=0.4.2
Requires-Dist: tomlkit>=0.13.0
Provides-Extra: amazon-braket
Requires-Dist: strangeworks-braket-extension; extra == 'amazon-braket'
Provides-Extra: qiskit-ionq
Requires-Dist: strangeworks-qiskit-ionq-extension; extra == 'qiskit-ionq'
